README.md
setup.py
realestateapplication.egg-info/PKG-INFO
realestateapplication.egg-info/SOURCES.txt
realestateapplication.egg-info/dependency_links.txt
realestateapplication.egg-info/top_level.txt
realestatevalidation/__init__.py