Metadata-Version: 2.1
Name: realestateapplication
Version: 0.2.0
Summary: A simple calculation for the realestate application
Home-page: UNKNOWN
Author: Rajkumar
Author-email: pmrajkumar30@gmail.com
License: UNKNOWN
Keywords: splittercalculation
Platform: UNKNOWN
Classifier: Development Status :: 3 - Alpha
Classifier: Programming Language :: Python :: 3
Classifier: License :: OSI Approved :: MIT License
Classifier: Operating System :: OS Independent
Requires-Python: >=3.6
